ansible_simple/__init__.py
ansible_simple/api.py
ansible_simple/result.py
ansible_simple-2.0.3.dist-info/LICENSE
ansible_simple-2.0.3.dist-info/METADATA
ansible_simple-2.0.3.dist-info/WHEEL
ansible_simple-2.0.3.dist-info/top_level.txt
ansible_simple-2.0.3.dist-info/RECORD
