Metadata-Version: 2.1
Name: ansible-simple
Version: 2.0.3
Summary: A simple SDK to use Ansible API.
Author-email: rayzh <kribugzzz@outlook.com>
Project-URL: Homepage, https://github.com/Lorryrui/ansbile_simple
Classifier: Programming Language :: Python :: 3
Classifier: License :: OSI Approved :: Apache Software License
Classifier: Operating System :: OS Independent
Requires-Python: >=3.10
License-File: LICENSE
Requires-Dist: ansible ==8.5.0
Requires-Dist: ansible-base ==2.10.17
